<annotation>
	<folder>3f</folder>
	<filename>image38.jpg</filename>
	<path>C:\Users\HP\PycharmProjects\Final Yr Pro\3f\image38.jpg</path>
	<source>
		<database>Unknown</database>
	</source>
	<size>
		<width>800</width>
		<height>410</height>
		<depth>3</depth>
	</size>
	<segmented>0</segmented>
	<object>
		<name>nonacc</name>
		<pose>Unspecified</pose>
		<truncated>0</truncated>
		<difficult>0</difficult>
		<bndbox>
			<xmin>324</xmin>
			<ymin>106</ymin>
			<xmax>346</xmax>
			<ymax>119</ymax>
		</bndbox>
	</object>
	<object>
		<name>nonacc</name>
		<pose>Unspecified</pose>
		<truncated>0</truncated>
		<difficult>0</difficult>
		<bndbox>
			<xmin>409</xmin>
			<ymin>99</ymin>
			<xmax>428</xmax>
			<ymax>111</ymax>
		</bndbox>
	</object>
	<object>
		<name>nonacc</name>
		<pose>Unspecified</pose>
		<truncated>0</truncated>
		<difficult>0</difficult>
		<bndbox>
			<xmin>602</xmin>
			<ymin>105</ymin>
			<xmax>702</xmax>
			<ymax>140</ymax>
		</bndbox>
	</object>
</annotation>
